timeplus_messaging/__init__.py
timeplus_messaging/admin.py
timeplus_messaging/consumer.py
timeplus_messaging/producer.py
timeplus_messaging/record.py
timeplus_messaging-0.0.3.dist-info/licenses/LICENSE
timeplus_messaging-0.0.3.dist-info/METADATA
timeplus_messaging-0.0.3.dist-info/WHEEL
timeplus_messaging-0.0.3.dist-info/top_level.txt
timeplus_messaging-0.0.3.dist-info/RECORD
