Metadata-Version: 2.4
Name: timeplus-messaging
Version: 0.0.3
Summary: Messaging library for Timeplus streams
Author-email: Gang Tao <gang@timeplus.io>
Classifier: Programming Language :: Python :: 3
Classifier: License :: OSI Approved :: MIT License
Classifier: Operating System :: OS Independent
Requires-Python: >=3.7
License-File: LICENSE
Requires-Dist: proton-driver
Provides-Extra: dev
Requires-Dist: pytest; extra == "dev"
Requires-Dist: pytest-cov; extra == "dev"
Requires-Dist: flake8>=5.0.4; extra == "dev"
Requires-Dist: black>=23.3.0; extra == "dev"
Dynamic: license-file
Dynamic: requires-python
